utboost/VERSION
utboost/__init__.py
utboost/basic.py
utboost/callback.py
utboost/core.py
utboost/libpath.py
utboost/metric.py
utboost/validation.py
utboost/lib/lib_utboost.so
utboost-0.1.7.dist-info/METADATA
utboost-0.1.7.dist-info/WHEEL
utboost-0.1.7.dist-info/top_level.txt
utboost-0.1.7.dist-info/RECORD
